django_global_context-0.1.1.dist-info/METADATA
django_global_context-0.1.1.dist-info/RECORD
django_global_context-0.1.1.dist-info/WHEEL
django_global_context-0.1.1.dist-info/top_level.txt
globalcontext/__init__.py
