Metadata-Version: 2.1
Name: django-global-context
Version: 0.1.1
Summary: Global context injector for Django
Home-page: https://github.com/ccnmtl/django-global-context
Author: Nik Nyby
Author-email: nnyby@columbia.edu
License: UNKNOWN
Platform: UNKNOWN
